fastapi_project_creator/__init__.py
fastapi_project_creator/main.py
fastapi_project_creator-0.2.2.dist-info/licenses/LICENSE
fastapi_project_creator-0.2.2.dist-info/METADATA
fastapi_project_creator-0.2.2.dist-info/WHEEL
fastapi_project_creator-0.2.2.dist-info/entry_points.txt
fastapi_project_creator-0.2.2.dist-info/top_level.txt
fastapi_project_creator-0.2.2.dist-info/RECORD
