Metadata-Version: 2.4
Name: fastapi-project-creator
Version: 0.2.2
Summary: CLI tool to generate FastAPI project structure
Home-page: https://github.com/raihanhd12/fastapi-project-creator
Author: Raihan Hidayatullah Djunaedi
Author-email: Raihan Hidayatullah Djunaedi <raihanhd.dev@gmail.com>
License: MIT
Project-URL: Homepage, https://github.com/raihanhd12/fastapi-project-creator
Project-URL: Bug Tracker, https://github.com/raihanhd12/fastapi-project-creator/issues
Keywords: fastapi,generator,template,cli
Classifier: Programming Language :: Python :: 3
Classifier: License :: OSI Approved :: MIT License
Classifier: Operating System :: OS Independent
Requires-Python: >=3.7
License-File: LICENSE
Dynamic: author
Dynamic: home-page
Dynamic: license-file
Dynamic: requires-python
